{"MPW46D_kurzusfelvetel":{"kurzusok":{"kurzus":[{"oktato":"Dr. Agárdi Anita","hely":"XXX.","idopont":{"vegpont":16,"nap":"hétfő","kezdopont":14},"kredit":5,"kurzusnev":"WEB technológiák I."},{"oktato":"Dr. Agárdi Anita","hely":"inf\/202.","idopont":{"vegpont":18,"nap":"hétfő","kezdopont":16},"kredit":5,"kurzusnev":"WEB technológiák I."},{"oktato":"Kunné Dr. Tamás Judit","hely":"XXXII.","idopont":{"vegpont":12,"nap":"kedd","kezdopont":10},"kredit":5,"kurzusnev":"Mesterséges intelligencia"},{"oktato":"Dr. Bednarik László","hely":"XXXII.","idopont":{"vegpont":14,"nap":"kedd","kezdopont":12},"kredit":5,"kurzusnev":"Adatkezelés XML-ben"},{"oktato":"Dr. Házy Attila","hely":"A1\/320.","idopont":{"vegpont":18,"nap":"kedd","kezdopont":14},"kredit":5,"kurzusnev":"Algoritmusok és vizsgálatuk"},{"oktato":"Dr. Bednarik László","hely":"inf\/103.","idopont":{"vegpont":14,"nap":"szerda","kezdopont":12},"kredit":5,"kurzusnev":"Adatkezelés XML-ben"},{"oktato":"Dr. Sasvári Péter","hely":"inf\/101.","idopont":{"vegpont":16,"nap":"szerda","kezdopont":14},"kredit":5,"kurzusnev":"Vállalati információs rendszerek fejlesztése"},{"oktato":"Dr. Sasvári Péter","hely":"inf\/101.","idopont":{"vegpont":20,"nap":"szerda","kezdopont":18},"kredit":5,"kurzusnev":"Vállalati információs rendszerek fejlesztése"},{"oktato":"Fazekas Levente","hely":"I.","idopont":{"vegpont":12,"nap":"csütörtök","kezdopont":10},"kredit":5,"kurzusnev":"Mesterséges intelligencia"}]},"hallgato":{"szulev":"2002-06-14","hnev":"Görög Krisztina Erzsébet","szak":"programtervező informatikus"}}}